odoo/addons/stock_scheduler_assignation_horizon/README.rst
odoo/addons/stock_scheduler_assignation_horizon/__init__.py
odoo/addons/stock_scheduler_assignation_horizon/__manifest__.py
odoo/addons/stock_scheduler_assignation_horizon/data/ir_config_parameter.xml
odoo/addons/stock_scheduler_assignation_horizon/i18n/stock_scheduler_assignation_horizon.pot
odoo/addons/stock_scheduler_assignation_horizon/migrations/14.0.1.0.1/pre-migration.py
odoo/addons/stock_scheduler_assignation_horizon/models/__init__.py
odoo/addons/stock_scheduler_assignation_horizon/models/procurement_group.py
odoo/addons/stock_scheduler_assignation_horizon/models/res_config_settings.py
odoo/addons/stock_scheduler_assignation_horizon/readme/CONTRIBUTORS.rst
odoo/addons/stock_scheduler_assignation_horizon/readme/DESCRIPTION.rst
odoo/addons/stock_scheduler_assignation_horizon/readme/ROADMAP.rst
odoo/addons/stock_scheduler_assignation_horizon/readme/USAGE.rst
odoo/addons/stock_scheduler_assignation_horizon/static/description/icon.png
odoo/addons/stock_scheduler_assignation_horizon/static/description/index.html
odoo/addons/stock_scheduler_assignation_horizon/tests/__init__.py
odoo/addons/stock_scheduler_assignation_horizon/tests/test_res_config_settings.py
odoo/addons/stock_scheduler_assignation_horizon/tests/test_res_config_settings_common.py
odoo/addons/stock_scheduler_assignation_horizon/views/res_config_settings_views.xml
odoo14_addon_stock_scheduler_assignation_horizon-14.0.1.1.0.dist-info/METADATA
odoo14_addon_stock_scheduler_assignation_horizon-14.0.1.1.0.dist-info/WHEEL
odoo14_addon_stock_scheduler_assignation_horizon-14.0.1.1.0.dist-info/top_level.txt
odoo14_addon_stock_scheduler_assignation_horizon-14.0.1.1.0.dist-info/RECORD
